simvue_cli/__init__.py
simvue_cli/actions.py
simvue_cli/config.py
simvue_cli/server.py
simvue_cli/validation.py
simvue_cli/cli/__init__.py
simvue_cli/cli/display.py
simvue_cli/push/__init__.py
simvue_cli/push/core.py
simvue_cli/push/delimited.py
simvue_cli/push/json.py
simvue_cli/push/validate.py
simvue_cli-1.2.2.dist-info/METADATA
simvue_cli-1.2.2.dist-info/WHEEL
simvue_cli-1.2.2.dist-info/entry_points.txt
simvue_cli-1.2.2.dist-info/licenses/LICENSE
simvue_cli-1.2.2.dist-info/RECORD
