Metadata-Version: 2.4
Name: simvue-cli
Version: 1.2.2
Summary: Command Line Interface for interaction with a Simvue v3 server
Project-URL: homepage, https://simvue.io
Project-URL: repository, https://github.com/simvue-io/simvue-cli
Project-URL: documentation, https://docs.simvue.io
Author-email: Simvue Development Team <info@simvue.io>
License-File: LICENSE
Keywords: alerting,metrics,metrics-gathering,monitoring,tracking
Classifier: Development Status :: 5 - Production/Stable
Classifier: Intended Audience :: Science/Research
Classifier: License :: OSI Approved :: Apache Software License
Classifier: Natural Language :: English
Classifier: Operating System :: Microsoft :: Windows
Classifier: Operating System :: Unix
Classifier: Programming Language :: Python :: 3
Classifier: Programming Language :: Python :: 3.10
Classifier: Programming Language :: Python :: 3.11
Classifier: Programming Language :: Python :: 3.12
Classifier: Programming Language :: Python :: 3.13
Classifier: Programming Language :: Python :: 3.14
Classifier: Topic :: Scientific/Engineering
Classifier: Topic :: System :: Monitoring
Classifier: Topic :: Utilities
Classifier: Typing :: Typed
Requires-Python: <3.15,>=3.10
Requires-Dist: click-log>=0.4.0
Requires-Dist: click-option-group>=0.5.7
Requires-Dist: click-params>=0.5.0
Requires-Dist: click>=8.1.8
Requires-Dist: more-itertools>=10.8.0
Requires-Dist: pydantic>=2.11.9
Requires-Dist: regex>=2024.11.6
Requires-Dist: requests>=2.32.3
Requires-Dist: simvue>=2.2.2
Requires-Dist: tabulate>=0.9.0
Requires-Dist: toml>=0.10.2
Requires-Dist: tqdm>=4.67.1
